arxiv_mcp_server/__init__.py
arxiv_mcp_server/__main__.py
arxiv_mcp_server/config.py
arxiv_mcp_server/server.py
arxiv_mcp_server/prompts/__init__.py
arxiv_mcp_server/prompts/deep_research_analysis_prompt.py
arxiv_mcp_server/prompts/handlers.py
arxiv_mcp_server/prompts/prompt_manager.py
arxiv_mcp_server/prompts/prompts.py
arxiv_mcp_server/resources/__init__.py
arxiv_mcp_server/resources/papers.py
arxiv_mcp_server/tools/__init__.py
arxiv_mcp_server/tools/download.py
arxiv_mcp_server/tools/list_papers.py
arxiv_mcp_server/tools/read_paper.py
arxiv_mcp_server/tools/search.py
paper_retrieval_mcp-0.4.6.dist-info/METADATA
paper_retrieval_mcp-0.4.6.dist-info/WHEEL
paper_retrieval_mcp-0.4.6.dist-info/entry_points.txt
paper_retrieval_mcp-0.4.6.dist-info/licenses/LICENSE
paper_retrieval_mcp-0.4.6.dist-info/RECORD
