Metadata-Version: 2.4
Name: paper-retrieval-mcp
Version: 0.4.6
Summary: A flexible arXiv search and analysis service with MCP protocol support - simplified version
Author-email: Joseph Blazick <blazickjp@amazon.com>
License: MIT
License-File: LICENSE
Keywords: academic,arxiv,mcp,papers,research
Classifier: Development Status :: 4 - Beta
Classifier: Intended Audience :: Developers
Classifier: Intended Audience :: Science/Research
Classifier: License :: OSI Approved :: MIT License
Classifier: Programming Language :: Python :: 3
Classifier: Programming Language :: Python :: 3.11
Classifier: Programming Language :: Python :: 3.12
Classifier: Topic :: Scientific/Engineering
Classifier: Topic :: Software Development :: Libraries :: Python Modules
Requires-Python: >=3.11
Requires-Dist: aiofiles>=23.2.1
Requires-Dist: aiohttp>=3.9.1
Requires-Dist: anyio>=4.2.0
Requires-Dist: arxiv>=2.1.0
Requires-Dist: certifi>=2024.7.4
Requires-Dist: httpx>=0.24.0
Requires-Dist: mcp>=1.2.0
Requires-Dist: pydantic-settings>=2.1.0
Requires-Dist: pydantic>=2.8.0
Requires-Dist: pymupdf4llm>=0.0.17
Requires-Dist: python-dateutil>=2.8.2
Requires-Dist: python-dotenv>=1.0.0
Requires-Dist: sse-starlette>=1.8.2
Requires-Dist: uvicorn>=0.30.0
Provides-Extra: dev
Requires-Dist: black>=23.3.0; extra == 'dev'
Provides-Extra: test
Requires-Dist: aioresponses>=0.7.6; extra == 'test'
Requires-Dist: pytest-asyncio>=0.23.5; extra == 'test'
Requires-Dist: pytest-cov>=4.1.0; extra == 'test'
Requires-Dist: pytest-mock>=3.10.0; extra == 'test'
Requires-Dist: pytest>=8.0.0; extra == 'test'
